setup.py
unicodedata.py
micropython_unicodedata.egg-info/PKG-INFO
micropython_unicodedata.egg-info/SOURCES.txt
micropython_unicodedata.egg-info/dependency_links.txt
micropython_unicodedata.egg-info/top_level.txt