Metadata-Version: 1.0
Name: micropython-unicodedata
Version: 0.0.1
Summary: Dummy unicodedata module for MicroPython
Home-page: https://github.com/micropython/micropython/issues/405
Author: MicroPython Developers
Author-email: micro-python@googlegroups.com
License: MIT
Platform: UNKNOWN
